./.coverage
./.coveragerc
./.env.example
./.gitignore
./.python-version
./PKG-INFO
./README.md
./__init__.py
./poetry.lock
./pyproject.toml
./pytest.ini
./run_basic_tests.sh
./run_tests.sh
./uv.lock
./audit_system/__init__.py
./audit_system/base.py
./audit_system/enums.py
./audit_system/orchestrator.py
./audit_system/utils.py
./audit_system/audit_api/__init__.py
./audit_system/audit_api/base.py
./audit_system/audit_api/iflytek/__init__.py
./audit_system/audit_api/iflytek/ifly_audit_api.py
./audit_system/strategy/__init__.py
./audit_system/strategy/base_strategy.py
./audit_system/strategy/text_strategy.py
./exceptions/__init__.py
./exceptions/base.py
./exceptions/codes.py
./exceptions/errs.py
./initialize/initialize.py
./metrology_auth/__init__.py
./metrology_auth/base.py
./metrology_auth/calc.py
./metrology_auth/conc.py
./metrology_auth/config_client.toml.findercache
./metrology_auth/errors.py
./metrology_auth/licc.py
./metrology_auth/ma-sdk-default.toml
./metrology_auth/ma-sdk.cfg.toml
./metrology_auth/ma-sdk.toml
./metrology_auth/ma_sdk_linux_x64.h
./metrology_auth/ma_sdk_macos_arm64.h
./metrology_auth/ma_sdk_windows.h
./metrology_auth/rep.py
./metrology_auth/include/ma_sdk.h
./metrology_auth/ma-sdk-cfg/config_ma-sdk.toml.findercache
./metrology_auth/ma-sdk-cfg/service_janus_1.0.0.findercache
./otlp/__init__.py
./otlp/ip.py
./otlp/sid.py
./otlp/args/__init__.py
./otlp/args/base.py
./otlp/args/metric.py
./otlp/args/node_log.py
./otlp/args/sid.py
./otlp/args/trace.py
./otlp/log_trace/__init__.py
./otlp/log_trace/base.py
./otlp/log_trace/node_log.py
./otlp/log_trace/node_trace_log.py
./otlp/log_trace/workflow_log.py
./otlp/metrics/consts.py
./otlp/metrics/meter.py
./otlp/metrics/metric.py
./otlp/trace/span.py
./otlp/trace/trace.py
./service/__init__.py
./service/base.py
./service/utils.py
./service/cache/base_cache.py
./service/cache/factory.py
./service/cache/redis_cache.py
./service/db/db_service.py
./service/db/factory.py
./service/kafka/factory.py
astron_agent_core_common-0.1.0.dist-info/METADATA
astron_agent_core_common-0.1.0.dist-info/WHEEL
astron_agent_core_common-0.1.0.dist-info/RECORD
