Metadata-Version: 2.4
Name: astron-agent-core-common
Version: 0.1.0
Summary: Astron core common utilities and services
Author-email: mingduan <mingduan@iflytek.com>
Requires-Python: >=3.9
Requires-Dist: confluent-kafka>=2.5.0
Requires-Dist: googleapis-common-protos==1.60.0
Requires-Dist: grpc-google-iam-v1==0.12.6
Requires-Dist: loguru>=0.7.2
Requires-Dist: opentelemetry-api>=1.25.0
Requires-Dist: opentelemetry-exporter-opencensus>=0.46b0
Requires-Dist: opentelemetry-exporter-otlp-proto-grpc>=1.25.0
Requires-Dist: opentelemetry-exporter-otlp>=1.25.0
Requires-Dist: opentelemetry-proto>=1.25.0
Requires-Dist: opentelemetry-sdk>=1.25.0
Requires-Dist: opentelemetry-semantic-conventions>=0.46b0
Requires-Dist: pydantic-settings>=2.10.1
Requires-Dist: pydantic>=2.9.2
Requires-Dist: python-dotenv>=1.0.1
Requires-Dist: sqlmodel>=0.0.14
Requires-Dist: toml>=0.10.2
Requires-Dist: websocket-client==1.8.0
Requires-Dist: websockets==12.0
Provides-Extra: dev
Requires-Dist: pytest-asyncio>=0.21.0; extra == 'dev'
Requires-Dist: pytest-cov>=4.0.0; extra == 'dev'
Requires-Dist: pytest-mock>=3.10.0; extra == 'dev'
Requires-Dist: pytest>=7.0.0; extra == 'dev'
